[
  { "nombre": "ABREGO ESPINOZA, ZAIRA MORENA", "curso": "1° 1ª", "netbook": 1 },
  { "nombre": "ALBORNOZ CAZON, ALAN ALEXANDER", "curso": "1° 1ª", "netbook": 2 },
  { "nombre": "ANDRACA AGUERO, IRINA ABIGAIL", "curso": "1° 1ª", "netbook": 3 },
  { "nombre": "AVILA TRIGO, JONAS GABRIEL", "curso": "1° 1ª", "netbook": 4 },
  { "nombre": "BECHARD, SILVIA MARIA JOSE", "curso": "1° 1ª", "netbook": 5 },
  { "nombre": "BUSTAMANTE, CATHERIN NATALY", "curso": "1° 1ª", "netbook": 6 },
  { "nombre": "CASTILLO, GUADALUPE JAZMIN", "curso": "1° 1ª", "netbook": 7 },
  { "nombre": "CATALDO OROSCO, LUCAS ARIEL", "curso": "1° 1ª", "netbook": 8 },
  { "nombre": "CORREAS CORNEJO, THIAGO JOAQUIN", "curso": "1° 1ª", "netbook": 9 },
  { "nombre": "DECIMA, FACUNDO EMANUEL", "curso": "1° 1ª", "netbook": 10 },
  { "nombre": "FERNANDEZ TRIGO, MERCEDES ANTONELLA", "curso": "1° 1ª", "netbook": 11 },
  { "nombre": "FUNES GAMBOA, MELANIE", "curso": "1° 1ª", "netbook": 12 },
  { "nombre": "GELVES ANDRADA, MIA AGOSTINA", "curso": "1° 1ª", "netbook": 13 },
  { "nombre": "GUTIERREZ, WALTER RICARDO", "curso": "1° 1ª", "netbook": 14 },
  { "nombre": "HERRERA ARAUCO, BENJAMIN MANUEL", "curso": "1° 1ª", "netbook": 15 },
  { "nombre": "LOVERA ESTRADA, SOFIA MELANIE", "curso": "1° 1ª", "netbook": 16 },
  { "nombre": "NARVAEZ CORTEZ, SOFIA ARIADNA", "curso": "1° 1ª", "netbook": 17 },
  { "nombre": "NAVEDA DELGADO, NAZARENO ELIAS", "curso": "1° 1ª", "netbook": 18 },
  { "nombre": "OROZCO, MILAGROS YASMIN", "curso": "1° 1ª", "netbook": 19 },
  { "nombre": "PAEZ SARAVIA, AXEL FACUNDO", "curso": "1° 1ª", "netbook": 20 },
  { "nombre": "PEREYRA, LUCIANA MARYSOL", "curso": "1° 1ª", "netbook": 21 },
  { "nombre": "QUIROGA TERRERA, GEREMIAS EXEQUIEL ISAIAS", "curso": "1° 1ª", "netbook": 22 },
  { "nombre": "SOTOMAYOR, JUAN MANUEL", "curso": "1° 1ª", "netbook": 23 },
  { "nombre": "TELLO, ALEXANDER NAHUEL", "curso": "1° 1ª", "netbook": 24 },
  { "nombre": "TORRES, DIEGO LIONEL", "curso": "1° 1ª", "netbook": 25 },
  { "nombre": "TRENTACOSTE LUCERO, DYLAN DANIEL", "curso": "1° 1ª", "netbook": 26 },
  { "nombre": "VARGAS, VICTORIA MACARENA", "curso": "1° 1ª", "netbook": 27 },
  { "nombre": "VELA, BIANCA ISAURA", "curso": "1° 1ª", "netbook": 28 },
  { "nombre": "VIDELA GUZMAN, ROMINA KAREN", "curso": "1° 1ª", "netbook": 29 },
  { "nombre": "VILLEGAS VILLAFAÑE, LUCAS EXEQUIEL", "curso": "1° 1ª", "netbook": 30 },

  { "nombre": "ACHUMA GUZMAN, ESTEFANIA SOLANGE", "curso": "1° 2ª", "netbook": 1 },
  { "nombre": "ARANGUEZ GALINDO, GAEL VICENTINO", "curso": "1° 2ª", "netbook": 2 },
  { "nombre": "BULACIO, MILAGROS LUNA", "curso": "1° 2ª", "netbook": 3 },
  { "nombre": "CABALLERO PAEZ, AILIN LUZ", "curso": "1° 2ª", "netbook": 4 },
  { "nombre": "CALIZAYA, JENNIFER VALENTINA", "curso": "1° 2ª", "netbook": 5 },
  { "nombre": "CHARROQUI DAVID, ANGEL TIZIANO", "curso": "1° 2ª", "netbook": 6 },
  { "nombre": "CORNEJO, GUADALUPE LUCIA", "curso": "1° 2ª", "netbook": 7 },
  { "nombre": "ERAZO, ELIAS LAUTARO RENE", "curso": "1° 2ª", "netbook": 8 },
  { "nombre": "FERNANDEZ FUNES, JONATHAN FEDERICO", "curso": "1° 2ª", "netbook": 9 },
  { "nombre": "GARCIA ULLOA, DAMARIS JAZMIN", "curso": "1° 2ª", "netbook": 10 },
  { "nombre": "LOBOS, CAETANO SANTINO", "curso": "1° 2ª", "netbook": 11 },
  { "nombre": "LOBOS LICANTICA, MARTINA AILIN", "curso": "1° 2ª", "netbook": 12 },
  { "nombre": "LOVERA ESTRADA, ANYELINA MARIA LUZ", "curso": "1° 2ª", "netbook": 13 },
  { "nombre": "MENDOZA, EMIR NAIR JOSHUA", "curso": "1° 2ª", "netbook": 14 },
  { "nombre": "MICHALIK, MARCOS NAHUEL", "curso": "1° 2ª", "netbook": 15 },
  { "nombre": "OLLARCE LOBOS, GUADALUPE ROSARIO", "curso": "1° 2ª", "netbook": 16 },
  { "nombre": "OVIEDO ROJAS, BENJAMIN IAN", "curso": "1° 2ª", "netbook": 17 },
  { "nombre": "PONCE, THIAGO ALEXANDER", "curso": "1° 2ª", "netbook": 18 },
  { "nombre": "PRADO, THIAGO JOAQUIN", "curso": "1° 2ª", "netbook": 19 },
  { "nombre": "RAMOS CARDOZO, ESTEBAN ANDRES", "curso": "1° 2ª", "netbook": 20 },
  { "nombre": "SANTANDER, XIMENA ABRIL", "curso": "1° 2ª", "netbook": 21 },
  { "nombre": "SILVA GARAY, LEONEL MAXIMILIANO", "curso": "1° 2ª", "netbook": 22 },
  { "nombre": "TERRERO, MAIARA MORENA", "curso": "1° 2ª", "netbook": 23 },
  { "nombre": "TONELLI FERNANDEZ, SAMUEL JESUS", "curso": "1° 2ª", "netbook": 24 },
  { "nombre": "TRIGO, GIOVANNI EXEQUIEL", "curso": "1° 2ª", "netbook": 25 },
  { "nombre": "VARGAS ARECHE, JUAN IGNACIO EZEQUIEL", "curso": "1° 2ª", "netbook": 26 },
  { "nombre": "VEGA, DULCE MILAGROS", "curso": "1° 2ª", "netbook": 27 },
  { "nombre": "VEGA, LUCIA ABIGAIL", "curso": "1° 2ª", "netbook": 28 },
  { "nombre": "ZARATE AMAJAYA, VERENICE HEIDY", "curso": "1° 2ª", "netbook": 29 },
  { "nombre": "MORALES PACHECO, SHARON SEBASTIAN", "curso": "1° 2ª", "netbook": 30 },

  { "nombre": "AHUMADA SISTERNA, AXEL", "curso": "1° 3ª", "netbook": 1 },
  { "nombre": "ALFONSO CUEVAS, JOAQUIN ALEJANDRO", "curso": "1° 3ª", "netbook": 2 },
  { "nombre": "ANDRADA, MARCOS GABRIEL", "curso": "1° 3ª", "netbook": 3 },
  { "nombre": "ARCE PERALTA, DYLAN SANTIAGO", "curso": "1° 3ª", "netbook": 4 },
  { "nombre": "ARTEAGA ESCUDERO, BAUTISTA MARTIN", "curso": "1° 3ª", "netbook": 5 },
  { "nombre": "BENGOLEA ARRIAGADA, MALENA AGOSTINA", "curso": "1° 3ª", "netbook": 6 },
  { "nombre": "CEJAS, ELIAS ZAIR", "curso": "1° 3ª", "netbook": 7 },
  { "nombre": "DURAN, LEANDRO YOEL", "curso": "1° 3ª", "netbook": 8 },
  { "nombre": "FERNANDEZ FUNES, JULIETA AGUSTINA", "curso": "1° 3ª", "netbook": 9 },
  { "nombre": "GARCIA, GUADALUPE PILAR", "curso": "1° 3ª", "netbook": 10 },
  { "nombre": "GIMENEZ, JONAS MARTIN", "curso": "1° 3ª", "netbook": 11 },
  { "nombre": "GOMEZ FIGUEROA, AZUL ARIANA", "curso": "1° 3ª", "netbook": 12 },
  { "nombre": "GOMEZ OVIEDO, BAUTISTA DAVID", "curso": "1° 3ª", "netbook": 13 },
  { "nombre": "GONZALEZ, ISMAEL EXEQUIEL", "curso": "1° 3ª", "netbook": 14 },
  { "nombre": "GONZALEZ, SANTIAGO FRANCO", "curso": "1° 3ª", "netbook": 15 },
  { "nombre": "HEREDIA, BRIANA LUDMILA", "curso": "1° 3ª", "netbook": 16 },
  { "nombre": "MAMANI MOLLO, IAN GONZALO", "curso": "1° 3ª", "netbook": 17 },
  { "nombre": "MONTIVERO RIVAROLA, CONCEPCION", "curso": "1° 3ª", "netbook": 18 },
  { "nombre": "PAEZ RIVAS, MORENA JULIE", "curso": "1° 3ª", "netbook": 19 },
  { "nombre": "RIVERO JUAREZ, LUCIANA ELIANE", "curso": "1° 3ª", "netbook": 20 },
  { "nombre": "RODRIGUEZ, TIZIANO BENJAMIN", "curso": "1° 3ª", "netbook": 21 },
  { "nombre": "RODRIGUEZ SOSA, LUCIANO BENJAMIN", "curso": "1° 3ª", "netbook": 22 },
  { "nombre": "ROJAS, ANGELINA LAILA", "curso": "1° 3ª", "netbook": 23 },
  { "nombre": "SAEZ MORENO, TIZIANO LIONEL", "curso": "1° 3ª", "netbook": 24 },
  { "nombre": "SEBALLE CAMANI, SAIRA SOLANGE", "curso": "1° 3ª", "netbook": 25 },
  { "nombre": "SILVA GALDAME, MAJO AILIN", "curso": "1° 3ª", "netbook": 26 },
  { "nombre": "TERRERO, JONATHAN XAVIER", "curso": "1° 3ª", "netbook": 27 },
  { "nombre": "TOMASSETTI OLLARCE, MAYDA JEMIMA", "curso": "1° 3ª", "netbook": 28 },

  { "nombre": "AVELLANEDA PEREZ, TAMARA ANA", "curso": "2° 1ª", "netbook": 1 },
  { "nombre": "CAMPOS, LIONEL", "curso": "2° 1ª", "netbook": 2 },
  { "nombre": "CUSI TARCAYA, MELISA NOELIA", "curso": "2° 1ª", "netbook": 3 },
  { "nombre": "ENCINAS, LUCIANA MACARENA", "curso": "2° 1ª", "netbook": 4 },
  { "nombre": "GALDAME, JULIETA MICAELA", "curso": "2° 1ª", "netbook": 5 },
  { "nombre": "GIAMPIETRI ZALAZAR, VALENTINA YASMIN", "curso": "2° 1ª", "netbook": 6 },
  { "nombre": "GUZMAN, GIULIANA PRISCILA", "curso": "2° 1ª", "netbook": 7 },
  { "nombre": "MANCILLA, JEREMIAS EXEQUIEL", "curso": "2° 1ª", "netbook": 8 },
  { "nombre": "MARDONES, LUCAS BENJAMIN", "curso": "2° 1ª", "netbook": 9 },
  { "nombre": "MOLINA, ANA", "curso": "2° 1ª", "netbook": 10 },
  { "nombre": "MOYANO PACHECO, IGNACIO MARTIN", "curso": "2° 1ª", "netbook": 11 },
  { "nombre": "OLMOS VALDEZ, PAULA LISET", "curso": "2° 1ª", "netbook": 12 },
  { "nombre": "OZAN, JULIAN LAUTARO", "curso": "2° 1ª", "netbook": 13 },
  { "nombre": "PAEZ, FABIO ALEJANDRO", "curso": "2° 1ª", "netbook": 14 },
  { "nombre": "PELOC, MARIA URSULA", "curso": "2° 1ª", "netbook": 15 },
  { "nombre": "PLATESE, ARIEL IGNACIO", "curso": "2° 1ª", "netbook": 16 },
  { "nombre": "PUEBLA BUSTOS, ENZO GUSTAVO", "curso": "2° 1ª", "netbook": 17 },
  { "nombre": "QUIROGA, DANA GISEL", "curso": "2° 1ª", "netbook": 18 },
  { "nombre": "REYES, ULISES MATIAS", "curso": "2° 1ª", "netbook": 19 },
  { "nombre": "SAEZ, SANTINO MARTIN", "curso": "2° 1ª", "netbook": 20 },
  { "nombre": "SALAS, LIONEL DYLAN", "curso": "2° 1ª", "netbook": 21 },
  { "nombre": "SALAS, SHERLI MILAGROS", "curso": "2° 1ª", "netbook": 22 },
  { "nombre": "SALAZAR, GABRIELA AILEN", "curso": "2° 1ª", "netbook": 23 },
  { "nombre": "SALVATICO CHANDIA, TATIANA VALENTINA", "curso": "2° 1ª", "netbook": 24 },
  { "nombre": "SANDOVAL AZCURRA, SANTIAGO MARTIN", "curso": "2° 1ª", "netbook": 25 },
  { "nombre": "SOSA ORTIZ, SOFIA EVANGELINA", "curso": "2° 1ª", "netbook": 26 },
  { "nombre": "VERDULLO, RAMIRO CATRIEL", "curso": "2° 1ª", "netbook": 27 },

  { "nombre": "ANDRADA, JULIA ISABEL", "curso": "2° 2ª", "netbook": 1 },
  { "nombre": "AVEZOU GIORGIO, JERONIMO", "curso": "2° 2ª", "netbook": 2 },
  { "nombre": "AVILA ROJAS, ZAHIRA ARIADNA", "curso": "2° 2ª", "netbook": 3 },
  { "nombre": "AZCURRA, IGNACIO NAHUEL", "curso": "2° 2ª", "netbook": 4 },
  { "nombre": "BLANCO, VALENTINA BELEN", "curso": "2° 2ª", "netbook": 5 },
  { "nombre": "ECHEGARAY, SOFIA YANEL", "curso": "2° 2ª", "netbook": 6 },
  { "nombre": "GALARZA GODOY, ALEX URIEL", "curso": "2° 2ª", "netbook": 7 },
  { "nombre": "GONZALEZ, CARLOS JESUS", "curso": "2° 2ª", "netbook": 8 },
  { "nombre": "GUARDIA LUCERO, JAZMIN ABIGAIL", "curso": "2° 2ª", "netbook": 9 },
  { "nombre": "GUTIERREZ VARGAS, DYLAN BENJAMIN", "curso": "2° 2ª", "netbook": 10 },
  { "nombre": "LOPEZ LUNA, MATIAS GERARDO", "curso": "2° 2ª", "netbook": 11 },
  { "nombre": "MATELUNA, JULIETA MILAGROS", "curso": "2° 2ª", "netbook": 12 },
  { "nombre": "MONTERO, NAZARENO FEDERICO", "curso": "2° 2ª", "netbook": 13 },
  { "nombre": "MORELLI, LEONEL IVAN", "curso": "2° 2ª", "netbook": 14 },
  { "nombre": "OLIVERA GOMEZ, NAHIARA MORENA", "curso": "2° 2ª", "netbook": 15 },
  { "nombre": "ORTIZ, MICAELA SOLANGE", "curso": "2° 2ª", "netbook": 16 },
  { "nombre": "ORTIZ ORTEGA, TIZIANA MIA", "curso": "2° 2ª", "netbook": 17 },
  { "nombre": "PUERTA LARA, MARIA PIA", "curso": "2° 2ª", "netbook": 18 },
  { "nombre": "PUSCAMA, ALMA NAZAREA", "curso": "2° 2ª", "netbook": 19 },
  { "nombre": "QUIROGA, LAUTARO JESUS", "curso": "2° 2ª", "netbook": 20 },
  { "nombre": "ROMANO CRUZ, LUCIANA MAGALI", "curso": "2° 2ª", "netbook": 21 },
  { "nombre": "SARAVIA, YOEL AGUSTIN", "curso": "2° 2ª", "netbook": 22 },
  { "nombre": "SUVIAURRE CISNEROS, ALAN JESUS", "curso": "2° 2ª", "netbook": 23 },
  { "nombre": "VEDIA, XIOMARA CAMILA", "curso": "2° 2ª", "netbook": 24 },
  { "nombre": "VERA TORRES, THIAGO BENJAMIN", "curso": "2° 2ª", "netbook": 25 },

  { "nombre": "ARAUZ, MARIA NAHIR ETHEL", "curso": "2° 3ª", "netbook": 1 },
  { "nombre": "BALMACEDA, ANA MARIA", "curso": "2° 3ª", "netbook": 2 },
  { "nombre": "BARZOLA, AILEN ADELA", "curso": "2° 3ª", "netbook": 3 },
  { "nombre": "BARZOLA, BELEN TERESA", "curso": "2° 3ª", "netbook": 4 },
  { "nombre": "CAZON RUEDA, LUZ KATIA", "curso": "2° 3ª", "netbook": 5 },
  { "nombre": "CHACON, LAUTARO BENJAMIN", "curso": "2° 3ª", "netbook": 6 },
  { "nombre": "CISTERNA RODRIGUEZ, LUISANA NICOL", "curso": "2° 3ª", "netbook": 7 },
  { "nombre": "CRUZ LUNA, DIEGO ALEXANDER", "curso": "2° 3ª", "netbook": 8 },
  { "nombre": "GALLARDO, GONZALO BENJAMIN", "curso": "2° 3ª", "netbook": 9 },
  { "nombre": "GOMEZ PRADO, MAXIMILIANO LIONEL", "curso": "2° 3ª", "netbook": 10 },
  { "nombre": "LIZARRAGA FERNANDEZ, RUBEN DARIO", "curso": "2° 3ª", "netbook": 11 },
  { "nombre": "LOPEZ, NATALIO JESUS", "curso": "2° 3ª", "netbook": 12 },
  { "nombre": "LUCONI, IVAN ERNESTO", "curso": "2° 3ª", "netbook": 13 },
  { "nombre": "MARTINEZ, SEBASTIAN LEONEL", "curso": "2° 3ª", "netbook": 14 },
  { "nombre": "MORALES, FACUNDO GABRIEL", "curso": "2° 3ª", "netbook": 15 },
  { "nombre": "MORALES, RENZO ISMAEL", "curso": "2° 3ª", "netbook": 16 },
  { "nombre": "PEREZ, MATIAS LIONEL", "curso": "2° 3ª", "netbook": 17 },
  { "nombre": "PIZARRO, BIANCA ABIGAIL", "curso": "2° 3ª", "netbook": 18 },
  { "nombre": "RIQUELME, THIAGO GABRIEL", "curso": "2° 3ª", "netbook": 19 },
  { "nombre": "ROBLES TOMASSI, JOAQUIN VICTOR", "curso": "2° 3ª", "netbook": 20 },
  { "nombre": "SAEZ MONDACA, ALEXIS BENJAMIN", "curso": "2° 3ª", "netbook": 21 },
  { "nombre": "SCAGLIONE, AGOSTINA SOFIA", "curso": "2° 3ª", "netbook": 22 },
  { "nombre": "SILVA GALDAME, CANDELA VICTORIA", "curso": "2° 3ª", "netbook": 23 },
  { "nombre": "VARGAS ARGUELLO, CARLOS HUGO", "curso": "2° 3ª", "netbook": 24 },
  { "nombre": "VARGAS GARCIA, AYMARA IVON", "curso": "2° 3ª", "netbook": 25 },
  
  { "nombre": "ARAUCO, MELANIE MILAGROS", "curso": "3° 1ª", "netbook": 7 },
  { "nombre": "BARBAS PERALTA, LUCIANO DANIEL", "curso": "3° 1ª", "netbook": 8 },
  { "nombre": "CORTES, CANDELA ITATI VALENTINA", "curso": "3° 1ª", "netbook": 9 },
  { "nombre": "DE FAVERI CICCHINELLI, URIEL NICOLAS", "curso": "3° 1ª", "netbook": 10 },
  { "nombre": "ECHEGARAY ANZORENA, JESUS EZEQUIEL", "curso": "3° 1ª", "netbook": 11 },
  { "nombre": "GONZALEZ LAGOS, MILAGROS GUADALUPE", "curso": "3° 1ª", "netbook": 12 },
  { "nombre": "GUEVARAS CARDENAS, AUGUSTO EZEQUIEL", "curso": "3° 1ª", "netbook": 13 },
  { "nombre": "JUAREZ LUNA, AXEL LIONEL", "curso": "3° 1ª", "netbook": 14 },
  { "nombre": "MENDEZ RIQUELME, LUZ AGUSTINA", "curso": "3° 1ª", "netbook": 15 },
  { "nombre": "MIRANDA, CELESTE LUCÍA", "curso": "3° 1ª", "netbook": 16 },
  { "nombre": "MOGRO LEON, LUDMILA MARIANELA", "curso": "3° 1ª", "netbook": 17 },
  { "nombre": "NUÑEZ, CANDELA LUCÍA", "curso": "3° 1ª", "netbook": 18 },
  { "nombre": "PAEZ, LUCILA MARIEL ESTEFANIA", "curso": "3° 1ª", "netbook": 19 },
  { "nombre": "PALACIOS BAYARRI, SHEILA AGUSTINA", "curso": "3° 1ª", "netbook": 20 },
  { "nombre": "PERALTA RUIZ, BRUNO ALEJANDRO", "curso": "3° 1ª", "netbook": 21 },
  { "nombre": "PEREZ ALTAMIRANO, MAILÉN YOSELIE", "curso": "3° 1ª", "netbook": 22 },
  { "nombre": "PRADO ALCAYAGA, MILAGROS EVANGELINA", "curso": "3° 1ª", "netbook": 23 },
  { "nombre": "RODRÍGUEZ, JAZMIN AGOSTINA", "curso": "3° 1ª", "netbook": 24 },
  { "nombre": "RODRIGUEZ VEDIA, ORIANA", "curso": "3° 1ª", "netbook": 25 },
  { "nombre": "SALTO, CANDELA SOLANGE", "curso": "3° 1ª", "netbook": 26 },
  { "nombre": "TRIGO PERALTA, ROCIO NAOMI", "curso": "3° 1ª", "netbook": 27 },
  { "nombre": "VARGAS GONZALEZ, SEBASTIÁN AGUSTÍN", "curso": "3° 1ª", "netbook": 28 },
  { "nombre": "VEGA, DEBORAH TATIANA", "curso": "3° 1ª", "netbook": 29 },
  { "nombre": "VILLAFAÑE, MARÍA AGUSTINA", "curso": "3° 1ª", "netbook": 30 },
  
  { "nombre": "CATALDO COSENTINO, ELUNEY NAHIARA", "curso": "3° 2ª", "netbook": 9 },
  { "nombre": "CHOQUE, AGUSTINA YANEL", "curso": "3° 2ª", "netbook": 10 },
  { "nombre": "CRUZ OZAN, GUADALUPE JAZMIN", "curso": "3° 2ª", "netbook": 11 },
  { "nombre": "GARCIA ULLOA, BENJAMÍN JOEL", "curso": "3° 2ª", "netbook": 12 },
  { "nombre": "GERLING, TIAGO NAIR", "curso": "3° 2ª", "netbook": 13 },
  { "nombre": "GIMENEZ, GUADALUPE BELEN", "curso": "3° 2ª", "netbook": 14 },
  { "nombre": "GOMEZ, ABIGAIL LOURDES", "curso": "3° 2ª", "netbook": 15 },
  { "nombre": "GUAJARDO, ELIAS GONZALO", "curso": "3° 2ª", "netbook": 16 },
  { "nombre": "GUIÑAZU, BARBARA AZUL", "curso": "3° 2ª", "netbook": 17 },
  { "nombre": "HERNANDEZ, SANTIAGO EXEQUIEL", "curso": "3° 2ª", "netbook": 18 },
  { "nombre": "MALDONADO CARRAZCO, MAITE SEYLA ABIGAIL", "curso": "3° 2ª", "netbook": 19 },
  { "nombre": "MARTINEZ, ROXANA NICOLE", "curso": "3° 2ª", "netbook": 20 },
  { "nombre": "MORAN ISAGUIRRE, SANTIAGO MATIAS", "curso": "3° 2ª", "netbook": 21 },
  { "nombre": "MORENO GODOY, PAULA ABRIL", "curso": "3° 2ª", "netbook": 22 },
  { "nombre": "RU, LEONARDO JOAQUÍN", "curso": "3° 2ª", "netbook": 23 },
  { "nombre": "SANCHEZ ORMACHEA, MARIANELA DEL VALLE", "curso": "3° 2ª", "netbook": 24 },
  { "nombre": "SUBELZA, ALVARO FABIAN", "curso": "3° 2ª", "netbook": 25 },
  { "nombre": "ULIARTE, MARIA CRISTINA", "curso": "3° 2ª", "netbook": 26 },
  { "nombre": "VEGA TICONA, AYELEN GISEL", "curso": "3° 2ª", "netbook": 27 },
  { "nombre": "VILLAFAÑE SOSA, JUAN MANUEL", "curso": "3° 2ª", "netbook": 28 },
  { "nombre": "VILLAMARIN, ZAHIRA ALDANA", "curso": "3° 2ª", "netbook": 29 },
  { "nombre": "ZARATE QUESPI, IAN LEANDRO LUCCA", "curso": "3° 2ª", "netbook": 30 },
  
  { "nombre": "ADARO BUENANUEVA, AGUSTINA CANDELA", "curso": "3° 3ª", "netbook": 12 },
  { "nombre": "BORDÓN, SOFÍA FLORENCIA", "curso": "3° 3ª", "netbook": 13 },
  { "nombre": "CHOQUE, TATIANA GUADALUPE", "curso": "3° 3ª", "netbook": 14 },
  { "nombre": "DOMINGUEZ, LARA SOLEDAD", "curso": "3° 3ª", "netbook": 15 },
  { "nombre": "FERNANDEZ CHAVEZ, MELANIE GEORGINA", "curso": "3° 3ª", "netbook": 16 },
  { "nombre": "HERRERA RIOS, VICTORIA DE LOS ANGELES", "curso": "3° 3ª", "netbook": 17 },
  { "nombre": "JOFRÉ, CANDELA MARIANA", "curso": "3° 3ª", "netbook": 18 },
  { "nombre": "LIZARDO, BRUNO SANTIAGO", "curso": "3° 3ª", "netbook": 19 },
  { "nombre": "OCAMPO SUBELZA, MARCOS EZEQUIEL", "curso": "3° 3ª", "netbook": 20 },
  { "nombre": "OLIVERA CASTILLO, SHIRLEY NAOMI", "curso": "3° 3ª", "netbook": 21 },
  { "nombre": "PEREA, MARISA TANIA", "curso": "3° 3ª", "netbook": 22 },
  { "nombre": "QUIROGA, MELISA ANTONELLA", "curso": "3° 3ª", "netbook": 23 },
  { "nombre": "RUEDA CRUZ, FEDERICO URIEL", "curso": "3° 3ª", "netbook": 24 },
  { "nombre": "SAEZ, BENJAMÍN DIDIER", "curso": "3° 3ª", "netbook": 25 },
  { "nombre": "TELLO, LAURA DANIELA", "curso": "3° 3ª", "netbook": 26 },
  { "nombre": "TRIGO, SOL MILAGROS", "curso": "3° 3ª", "netbook": 27 },
  { "nombre": "VIDELA, TIZIANA ANGELINA", "curso": "3° 3ª", "netbook": 28 },
  { "nombre": "ZARATE, IGNACIO VALENTΙΝΟ", "curso": "3° 3ª", "netbook": 29 },
  { "nombre": "ZURRIABLE LUCERO, VALENTINA MAIA ESTER", "curso": "3° 3ª", "netbook": 30 },
  
  { "nombre": "AGUIRRE GATICA, THIAGO MAURICIO", "curso": "4° 1ª", "netbook": 1 },
  { "nombre": "ARENAS SALAZAR, TALIA XIOMARA", "curso": "4° 1ª", "netbook": 2 },
  { "nombre": "ATENCIO VALDEZ, TANIA NEREA", "curso": "4° 1ª", "netbook": 3 },
  { "nombre": "BURGOA, BRIAN LAUTARO", "curso": "4° 1ª", "netbook": 4 },
  { "nombre": "CASANOVA, AXEL EMILIANO", "curso": "4° 1ª", "netbook": 5 },
  { "nombre": "CASTRO MOGRO, GUADALUPE NATALIA", "curso": "4° 1ª", "netbook": 6 },
  { "nombre": "CHIRINO LA ROSA, GERONIMO EZEQUIEL", "curso": "4° 1ª", "netbook": 7 },
  { "nombre": "CORDERO LUNA, TANIA CLARA", "curso": "4° 1ª", "netbook": 8 },
  { "nombre": "CORNEJO, JULIAN SEBASTIAN", "curso": "4° 1ª", "netbook": 9 },
  { "nombre": "CORREAS CORNEJO, MARTINA CELESTE", "curso": "4° 1ª", "netbook": 10 },
  { "nombre": "DIAZ MENDEZ, EMMA VALENTINA", "curso": "4° 1ª", "netbook": 11 },
  { "nombre": "FIAÑO ESCUDERO, LOURDES VICTORIA", "curso": "4° 1ª", "netbook": 12 },
  { "nombre": "GOMEZ OVIEDO, PABLO JOAQUÍN", "curso": "4° 1ª", "netbook": 13 },
  { "nombre": "LEAL MESINA, NARELLA NAHIR", "curso": "4° 1ª", "netbook": 14 },
  { "nombre": "LIZARRAGA, DANIEL ALEJANDRO", "curso": "4° 1ª", "netbook": 15 },
  { "nombre": "LOPEZ, MARIA CIELO ROGELIA", "curso": "4° 1ª", "netbook": 16 },
  { "nombre": "LOPEZ OLGUIN, TIZIANO ESTEBAN", "curso": "4° 1ª", "netbook": 17 },
  { "nombre": "MANCILLA, GUADALUPE JAZMÍN", "curso": "4° 1ª", "netbook": 18 },
  { "nombre": "MIRANDA, LOURDES ALICIA", "curso": "4° 1ª", "netbook": 19 },
  { "nombre": "MIRANDA DELGADO, VICTORIA CELESTE", "curso": "4° 1ª", "netbook": 20 },
  { "nombre": "MONDACA, JEREMIAS JOMIL", "curso": "4° 1ª", "netbook": 21 },
  { "nombre": "MONTIVERO RIVAROLA, MILAGROS", "curso": "4° 1ª", "netbook": 22 },
  { "nombre": "ORTIZ, ALEJO GIANLUCA", "curso": "4° 1ª", "netbook": 23 },
  { "nombre": "QUIROGA GUIÑAZÚ, MORENA MARA", "curso": "4° 1ª", "netbook": 24 },
  { "nombre": "RODRIGUEZ, BENJAMIN ALEXANDER", "curso": "4° 1ª", "netbook": 25 },
  { "nombre": "SAEZ MONDACA, ARIAN ISMAEL", "curso": "4° 1ª", "netbook": 26 },
  { "nombre": "SANTANDER, MARIA ANGEL", "curso": "4° 1ª", "netbook": 27 },
  { "nombre": "SOSA NUÑEZ, MELINA SOL ESMERALDA", "curso": "4° 1ª", "netbook": 28 },
  { "nombre": "TRIGO PAEZ, URIEL EMANUEL", "curso": "4° 1ª", "netbook": 29 },
  { "nombre": "ULIARTE, DAMIAN CEFERINO", "curso": "4° 1ª", "netbook": 30 },
  
  { "nombre": "AGNENI ROJAS, TIZIANA MARIEL", "curso": "4° 2ª", "netbook": 6 },
  { "nombre": "ALTAMIRANDA RODRIGUEZ, AXEL XAVIER", "curso": "4° 2ª", "netbook": 7 },
  { "nombre": "ARANGUEZ STOCCO, EZEQUIEL NICOLAS", "curso": "4° 2ª", "netbook": 8 },
  { "nombre": "BELLON, MILAGROS EVELYN MARTINA", "curso": "4° 2ª", "netbook": 9 },
  { "nombre": "CAMPOS, OWEN JESUS", "curso": "4° 2ª", "netbook": 10 },
  { "nombre": "CARRIZO, LUDMILA DAIAΝΑ", "curso": "4° 2ª", "netbook": 11 },
  { "nombre": "CASANOVA, FABRICIO AGUSTÍN", "curso": "4° 2ª", "netbook": 12 },
  { "nombre": "ENCINAS, BRISA JULIANA", "curso": "4° 2ª", "netbook": 13 },
  { "nombre": "FERNANDEZ, LAUREANO", "curso": "4° 2ª", "netbook": 14 },
  { "nombre": "GALLARDO, RODRIGO", "curso": "4° 2ª", "netbook": 15 },
  { "nombre": "GONZALEZ LAGOS, JULIETA MARIANELA", "curso": "4° 2ª", "netbook": 16 },
  { "nombre": "LEON, MELINA CANDELA", "curso": "4° 2ª", "netbook": 17 },
  { "nombre": "LIZARRAGA, AXEL GABRIEL", "curso": "4° 2ª", "netbook": 18 },
  { "nombre": "LOBOS LICANTICA, EVELYN XIOMARA", "curso": "4° 2ª", "netbook": 19 },
  { "nombre": "LOPÉZ ESCOBAR, BERNARDINA SELENE", "curso": "4° 2ª", "netbook": 20 },
  { "nombre": "MAMANI ALTAMIRANO, ZARA", "curso": "4° 2ª", "netbook": 21 },
  { "nombre": "MANSILLA GALLEGOS, FABRICIO ROMÁN", "curso": "4° 2ª", "netbook": 22 },
  { "nombre": "MARIN CARDOZO, JESUS CATRIEL", "curso": "4° 2ª", "netbook": 23 },
  { "nombre": "MORAN GUEVARA, MARTINA", "curso": "4° 2ª", "netbook": 24 },
  { "nombre": "PIZARRO, MARTÍN ARIEL", "curso": "4° 2ª", "netbook": 25 },
  { "nombre": "SAEZ, AZUL NAHIR", "curso": "4° 2ª", "netbook": 26 },
  { "nombre": "SZODO RODRÍGUEZ, THIAGO ALEJANDRO", "curso": "4° 2ª", "netbook": 27 },
  { "nombre": "VERDULLO, PAULO EXEQUIEL", "curso": "4° 2ª", "netbook": 28 },
  { "nombre": "VIDELA, BAUTISTA SAMUEL", "curso": "4° 2ª", "netbook": 29 },
  { "nombre": "VIDELA, DANIEL ARIEL", "curso": "4° 2ª", "netbook": 30 },
  
  { "nombre": "ARANCIBIA, MILENA JAZMÍN", "curso": "5° 1ª", "netbook": 6 },
  { "nombre": "ARANGUEZ PERALTA, JEREMÍAS JOAQUÍN", "curso": "5° 1ª", "netbook": 7 },
  { "nombre": "BELLON ROJAS, ELIAS RODRIGO EXEQUIEL", "curso": "5° 1ª", "netbook": 8 },
  { "nombre": "BRIZUELA, GIULIANA ELIZABETH", "curso": "5° 1ª", "netbook": 9 },
  { "nombre": "BRIZUELA, ROLANDO PEDRO DAVID", "curso": "5° 1ª", "netbook": 10 },
  { "nombre": "CASTILLO, LUNA AYMARA", "curso": "5° 1ª", "netbook": 11 },
  { "nombre": "DELGADO, SILVANA MAILEN", "curso": "5° 1ª", "netbook": 12 },
  { "nombre": "GIL ASCANIO, FLAVIA DANIELA", "curso": "5° 1ª", "netbook": 13 },
  { "nombre": "GODOY DEL CASTILLO, ANGEL GABRIEL", "curso": "5° 1ª", "netbook": 14 },
  { "nombre": "GONZALEZ SAEZ, TIAGO FABIAN", "curso": "5° 1ª", "netbook": 15 },
  { "nombre": "MARQUEZ, ANGEL NICOLAS", "curso": "5° 1ª", "netbook": 16 },
  { "nombre": "MERCADO, LUCAS EXEQUIEL", "curso": "5° 1ª", "netbook": 17 },
  { "nombre": "MOLINA, BAUTISTA", "curso": "5° 1ª", "netbook": 18 },
  { "nombre": "MONTOYA MAMANÍ, LAUTARO EZEQUIEL", "curso": "5° 1ª", "netbook": 19 },
  { "nombre": "MUÑOZ ALFARO, SOFIA MELANIE", "curso": "5° 1ª", "netbook": 20 },
  { "nombre": "NOVELINO HERRERA, MORENA ESTEFANIA", "curso": "5° 1ª", "netbook": 21 },
  { "nombre": "OLGUIN CASTILLO, ANELEY ORIANA", "curso": "5° 1ª", "netbook": 22 },
  { "nombre": "PINTOS CUEVAS, LAUTARO EXEQUIEL", "curso": "5° 1ª", "netbook": 23 },
  { "nombre": "PLATESE, CHIARA SHIRLEY", "curso": "5° 1ª", "netbook": 24 },
  { "nombre": "QUIROGA, LEONARDO NICOLAS", "curso": "5° 1ª", "netbook": 25 },
  { "nombre": "ROJAS, AXEL LAUTARO", "curso": "5° 1ª", "netbook": 26 },
  { "nombre": "SOSA ARENAS, YASMIN TRINIDAD", "curso": "5° 1ª", "netbook": 27 },
  { "nombre": "SOSA SILVA, CLAUDIA MELANIE", "curso": "5° 1ª", "netbook": 28 },
  { "nombre": "TOMASSETTI OLLARCE, SANTIAGO ALEXANDER", "curso": "5° 1ª", "netbook": 29 },
  { "nombre": "VILLAFAÑE, JULIAN DARIO", "curso": "5° 1ª", "netbook": 30 },
  
  { "nombre": "AHUMADA RAMON, PILAR", "curso": "5° 2ª", "netbook": 4 },
  { "nombre": "ALBORNOZ, ARIEL MACIEL", "curso": "5° 2ª", "netbook": 5 },
  { "nombre": "GALDAME, JOSEFINA MARIA DE LOS ANGELES", "curso": "5° 2ª", "netbook": 6 },
  { "nombre": "GARAÑIZ, FACUNDO ADOLFO", "curso": "5° 2ª", "netbook": 7 },
  { "nombre": "GELVES ANDRADA, JEREMIAS EZEQUIEL", "curso": "5° 2ª", "netbook": 8 },
  { "nombre": "HERRERA RIOS, GUADALUPE DEL VALLE", "curso": "5° 2ª", "netbook": 9 },
  { "nombre": "MANSILLA CHANDIA, JESABEL MILENA", "curso": "5° 2ª", "netbook": 10 },
  { "nombre": "MAROTO, AUGUSTO", "curso": "5° 2ª", "netbook": 11 },
  { "nombre": "MARTINEZ, KEVIN NAHUEL", "curso": "5° 2ª", "netbook": 12 },
  { "nombre": "MARTINEZ, TOMÁS", "curso": "5° 2ª", "netbook": 13 },
  { "nombre": "MASSIERO, MARÍA GUADALUPE", "curso": "5° 2ª", "netbook": 14 },
  { "nombre": "MONTES, FRANCO RAMON", "curso": "5° 2ª", "netbook": 15 },
  { "nombre": "OLIVERA, ARIADNA VALENΤΙΝΑ", "curso": "5° 2ª", "netbook": 16 },
  { "nombre": "ORTIZ PERALTA, MAYERLY SHAIRA", "curso": "5° 2ª", "netbook": 17 },
  { "nombre": "QUINTANILLA, IVAN URIEL", "curso": "5° 2ª", "netbook": 18 },
  { "nombre": "RAMOS GENTILE, KARIEL NAHUEL", "curso": "5° 2ª", "netbook": 19 },
  { "nombre": "RIQUELME, THIAGO FEDERICO", "curso": "5° 2ª", "netbook": 20 },
  { "nombre": "RODRIGUEZ, CAMILA", "curso": "5° 2ª", "netbook": 21 },
  { "nombre": "RODRIGUEZ, URIEL LAUTARO", "curso": "5° 2ª", "netbook": 22 },
  { "nombre": "ROMERO, AGOSTINA MARIANA", "curso": "5° 2ª", "netbook": 23 },
  { "nombre": "SALAS, VALENTINA NEREA", "curso": "5° 2ª", "netbook": 24 },
  { "nombre": "SAVINA TALAGUIRRE, JOAQUÍN EMILIANO", "curso": "5° 2ª", "netbook": 25 },
  { "nombre": "SEJAS, ALEXANDER ANGEL", "curso": "5° 2ª", "netbook": 26 },
  { "nombre": "TERRERO, VIOLETA ANA AGUSTINA", "curso": "5° 2ª", "netbook": 27 },
  { "nombre": "VEGA BARRIOS, GADIEL ELIAS", "curso": "5° 2ª", "netbook": 28 },
  { "nombre": "VERGARA QUERO, URIEL MAXIMILIANO", "curso": "5° 2ª", "netbook": 29 },
  { "nombre": "ZAPATA JEREZ, GABRIEL AUGUSTO", "curso": "5° 2ª", "netbook": 30 }
  
]
